textemotion.py
textemotion_ai.py
textemotion_ai-0.0.2.dist-info/METADATA
textemotion_ai-0.0.2.dist-info/WHEEL
textemotion_ai-0.0.2.dist-info/entry_points.txt
textemotion_ai-0.0.2.dist-info/top_level.txt
textemotion_ai-0.0.2.dist-info/RECORD
