Metadata-Version: 2.1
Name: textemotion-ai
Version: 0.0.2
Summary: make a pypi
Home-page: https://github.com/spcnkonno/textemotion_ai
Author: spcnkonno
Author-email: nkonno@sciencepark.co.jp
License: UNKNOWN
Project-URL: Bug Tracker, https://github.com/spcnkonno/textemotion_ai
Platform: UNKNOWN
Classifier: Programming Language :: Python :: 3
Classifier: License :: OSI Approved :: MIT License
Requires-Python: >=3.8.10
